src/postgres/__init__.py
src/postgres/implementation_instructions.md
src/postgres/server.py
iflow_mcp_simple_psql_mcp-1.0.2.dist-info/METADATA
iflow_mcp_simple_psql_mcp-1.0.2.dist-info/WHEEL
iflow_mcp_simple_psql_mcp-1.0.2.dist-info/entry_points.txt
iflow_mcp_simple_psql_mcp-1.0.2.dist-info/licenses/LICENSE
iflow_mcp_simple_psql_mcp-1.0.2.dist-info/RECORD
