Metadata-Version: 2.4
Name: iflow-mcp_simple-psql-mcp
Version: 1.0.2
Summary: A PostgreSQL MCP server project
Author-email: Netanel Bollag <nbollag@gmail.com>
License-File: LICENSE
Requires-Python: >=3.13
Requires-Dist: aiohttp>=3.11.13
Requires-Dist: asyncpg>=0.29.0
Requires-Dist: mcp[cli]>=1.3.0
Requires-Dist: pyyaml>=6.0.2
